pz_rail_calib-0.0.2.dist-info/licenses/LICENSE
rail/calib/__init__.py
rail/calib/_version.py
rail/calib/cell_assignment.py
rail/calib/cell_assignment_estimator.py
rail/calib/cell_assignment_funcs.py
rail/pipelines/calib/estimate_recalib.py
rail/pipelines/calib/inform_recalib.py
rail/pipelines/calib/inform_somlike.py
rail/pipelines/calib/somlike_recalib.py
rail/utils/recalib_algo_library.py
pz_rail_calib-0.0.2.dist-info/METADATA
pz_rail_calib-0.0.2.dist-info/WHEEL
pz_rail_calib-0.0.2.dist-info/top_level.txt
pz_rail_calib-0.0.2.dist-info/RECORD
