Metadata-Version: 2.4
Name: pz-rail-calib
Version: 0.0.2
Author-email: "LSST Dark Energy Science Collaboration (DESC)" <lsst-desc-rail-admin@slac.stanford.edu>
License: MIT License
Classifier: Development Status :: 4 - Beta
Classifier: License :: OSI Approved :: MIT License
Classifier: Intended Audience :: Developers
Classifier: Intended Audience :: Science/Research
Classifier: Operating System :: OS Independent
Classifier: Programming Language :: Python
Requires-Python: >=3.10
License-File: LICENSE
Requires-Dist: pz-rail-base>=1.1.6
Requires-Dist: pz-rail-sompz
Requires-Dist: ceci>=2.1
Requires-Dist: qp-prob[full]
Requires-Dist: numpy
Provides-Extra: dev
Requires-Dist: pytest; extra == "dev"
Requires-Dist: pytest-cov; extra == "dev"
Requires-Dist: pre-commit; extra == "dev"
Requires-Dist: pylint; extra == "dev"
Dynamic: license-file
